[
    {
      "TagSection": [
        {
          "name": "Event",
          "value": "FIDE Grand Prix 1 Playoff"
        },
        {
          "name": "Site",
          "value": "Berlin GER"
        },
        {
          "name": "Date",
          "value": "2022.02.17"
        },
        {
          "name": "Round",
          "value": "2.1"
        },
        {
          "name": "White",
          "value": "Nakamura, Hikaru"
        },
        {
          "name": "Black",
          "value": "Aronian, Levon"
        },
        {
          "name": "Result",
          "value": "1/2-1/2"
        },
        {
          "name": "WhiteTitle",
          "value": "GM"
        },
        {
          "name": "BlackTitle",
          "value": "GM"
        },
        {
          "name": "WhiteElo",
          "value": "2736"
        },
        {
          "name": "BlackElo",
          "value": "2772"
        },
        {
          "name": "ECO",
          "value": "C88"
        },
        {
          "name": "Opening",
          "value": "Ruy Lopez"
        },
        {
          "name": "Variation",
          "value": "closed, 7...O-O"
        },
        {
          "name": "WhiteFideId",
          "value": "2016192"
        },
        {
          "name": "BlackFideId",
          "value": "13300474"
        },
        {
          "name": "EventDate",
          "value": "2022.02.12"
        }
      ],
      "MovementSection": [
        {
          "whiteActions": [
            {
              "actionName": "Movement",
              "arguments": {
                "piece": "Pawn",
                "fromRow": "",
                "fromColumn": "",
                "toSquare": "e4",
                "isCapturing": "False"
              }
            }
          ],
          "blackActions": [
            {
              "actionName": "Movement",
              "arguments": {
                "piece": "Pawn",
                "fromRow": "",
                "fromColumn": "",
                "toSquare": "e5",
                "isCapturing": "False"
              }
            }
          ]
        },
        {
          "whiteActions": [
            {
              "actionName": "Movement",
              "arguments": {
                "piece": "Knight",
                "fromRow": "",
                "fromColumn": "",
                "toSquare": "f3",
                "isCapturing": "False"
              }
            }
          ],
          "blackActions": [
            {
              "actionName": "Movement",
              "arguments": {
                "piece": "Knight",
                "fromRow": "",
                "fromColumn": "",
                "toSquare": "c6",
                "isCapturing": "False"
              }
            }
          ]
        },
        {
          "whiteActions": [
            {
              "actionName": "Movement",
              "arguments": {
                "piece": "Bishop",
                "fromRow": "",
                "fromColumn": "",
                "toSquare": "b5",
                "isCapturing": "False"
              }
            }
          ],
          "blackActions": [
            {
              "actionName": "Movement",
              "arguments": {
                "piece": "Knight",
                "fromRow": "",
                "fromColumn": "",
                "toSquare": "f6",
                "isCapturing": "False"
              }
            }
          ]
        },
        {
          "whiteActions": [
            {
              "actionName": "Castle",
              "arguments": {
                "type": "short"
              }
            }
          ],
          "blackActions": [
            {
              "actionName": "Movement",
              "arguments": {
                "piece": "Bishop",
                "fromRow": "",
                "fromColumn": "",
                "toSquare": "e7",
                "isCapturing": "False"
              }
            }
          ]
        },
        {
          "whiteActions": [
            {
              "actionName": "Movement",
              "arguments": {
                "piece": "Rook",
                "fromRow": "",
                "fromColumn": "",
                "toSquare": "e1",
                "isCapturing": "False"
              }
            }
          ],
          "blackActions": [
            {
              "actionName": "Movement",
              "arguments": {
                "piece": "Pawn",
                "fromRow": "",
                "fromColumn": "",
                "toSquare": "e5",
                "isCapturing": "False"
              }
            }
          ]
        },
        {
          "whiteActions": [
            {
              "actionName": "Movement",
              "arguments": {
                "piece": "Bishop",
                "fromRow": "",
                "fromColumn": "",
                "toSquare": "b3",
                "isCapturing": "False"
              }
            }
          ],
          "blackActions": [
            {
              "actionName": "Castle",
              "arguments": {
                "type": "short"
              }
            }
          ]
        },
        {
          "whiteActions": [
            {
              "actionName": "Movement",
              "arguments": {
                "piece": "Pawn",
                "fromRow": "",
                "fromColumn": "",
                "toSquare": "h3",
                "isCapturing": "False"
              }
            }
          ],
          "blackActions": [
            {
              "actionName": "Movement",
              "arguments": {
                "piece": "Bishop",
                "fromRow": "",
                "fromColumn": "",
                "toSquare": "b7",
                "isCapturing": "False"
              }
            }
          ]
        },
        {
          "whiteActions": [
            {
              "actionName": "Movement",
              "arguments": {
                "piece": "Pawn",
                "fromRow": "",
                "fromColumn": "",
                "toSquare": "d3",
                "isCapturing": "False"
              }
            }
          ],
          "blackActions": [
            {
              "actionName": "Movement",
              "arguments": {
                "piece": "Pawn",
                "fromRow": "",
                "fromColumn": "",
                "toSquare": "d6",
                "isCapturing": "False"
              }
            }
          ]
        },
        {
          "whiteActions": [
            {
              "actionName": "Movement",
              "arguments": {
                "piece": "Pawn",
                "fromRow": "",
                "fromColumn": "",
                "toSquare": "a3",
                "isCapturing": "False"
              }
            }
          ],
          "blackActions": [
            {
              "actionName": "Movement",
              "arguments": {
                "piece": "Queen",
                "fromRow": "",
                "fromColumn": "",
                "toSquare": "d7",
                "isCapturing": "False"
              }
            }
          ]
        },
        {
          "whiteActions": [
            {
              "actionName": "Movement",
              "arguments": {
                "piece": "Knight",
                "fromRow": "",
                "fromColumn": "",
                "toSquare": "c3",
                "isCapturing": "False"
              }
            }
          ],
          "blackActions": [
            {
              "actionName": "Movement",
              "arguments": {
                "piece": "Knight",
                "fromRow": "",
                "fromColumn": "",
                "toSquare": "d8",
                "isCapturing": "False"
              }
            }
          ]
        },
        {
          "whiteActions": [
            {
              "actionName": "Movement",
              "arguments": {
                "piece": "Knight",
                "fromRow": "",
                "fromColumn": "",
                "toSquare": "h2",
                "isCapturing": "False"
              }
            }
          ],
          "blackActions": [
            {
              "actionName": "Movement",
              "arguments": {
                "piece": "Knight",
                "fromRow": "",
                "fromColumn": "",
                "toSquare": "e6",
                "isCapturing": "False"
              }
            }
          ]
        },
        {
          "whiteActions": [
            {
              "actionName": "Movement",
              "arguments": {
                "piece": "Knight",
                "fromRow": "",
                "fromColumn": "",
                "toSquare": "g4",
                "isCapturing": "False"
              }
            }
          ],
          "blackActions": [
            {
              "actionName": "Movement",
              "arguments": {
                "piece": "King",
                "fromRow": "",
                "fromColumn": "",
                "toSquare": "h8",
                "isCapturing": "False"
              }
            }
          ]
        },
        {
          "whiteActions": [
            {
              "actionName": "Movement",
              "arguments": {
                "capturer": "Knight",
                "fromRow": "",
                "fromColumn": "",
                "toSquare": "f6",
                "isCapturing": "True"
              }
            }
          ],
          "blackActions": [
            {
              "actionName": "Capture",
              "arguments": {
                "capturer": "Bishop",
                "fromRow": "",
                "fromColumn": "",
                "toSquare": "f6",
                "isCapturing": "False"
              }
            }
          ]
        },
        {
          "whiteActions": [
            {
              "actionName": "Movement",
              "arguments": {
                "piece": "Pawn",
                "fromRow": "",
                "fromColumn": "",
                "toSquare": "d3",
                "isCapturing": "False"
              }
            }
          ],
          "blackActions": [
            {
              "actionName": "Movement",
              "arguments": {
                "piece": "Pawn",
                "fromRow": "",
                "fromColumn": "",
                "toSquare": "d6",
                "isCapturing": "False"
              }
            }
          ]
        }
      ]
    }
]