[
    {
        "tagSection" : [
            {"name": "blah", "value": "blah"}
        ],
    }
        "movetextSection": [
            { ( e8=N+ e5)
                "whiteActions": [
                    {
                        "actionName": "Movement",
                        "arguments": {
                            "piece": "Pawn",
                            "fromRow": "",
                            "fromCol": "",
                            "toSquare": "e8",
                            "isCapturing": False
                        }
                    },
                    {
                        "actionName": "Promotes",
                        "arguments": {
                            "fromCol": "e",
                            "promotionPiece" : "Knight"
                        }
                    },
                    {
                        "actionName": "Check",
                        "arguments": {}
                    },
                    {
                        "actionName": ""
                    }
                ],
                "blackActions": [
                    {
                        "actionName": "Movement",
                        "arguments": {
                            "piece": "Pawn",
                            "fromRow": "",
                            "fromCol": "",
                            "toSquare": "e5",
                            "isCapturing": 
                        }
                    },
                ]
            }
        ]
    }
]

"Movement", "Castle" ("type": (long/short)), "Promotes", "Check", "Checkmate"